lcp_deep_research_mcp/__init__.py
lcp_deep_research_mcp/server.py
lcp_deep_research_mcp-0.1.5.dist-info/METADATA
lcp_deep_research_mcp-0.1.5.dist-info/WHEEL
lcp_deep_research_mcp-0.1.5.dist-info/entry_points.txt
lcp_deep_research_mcp-0.1.5.dist-info/RECORD
