Metadata-Version: 2.4
Name: lcp-deep-research-mcp
Version: 0.1.5
Summary: 一個 MCP 伺服器，提供統一的網路和學術搜尋研究工具
Requires-Dist: beautifulsoup4
Requires-Dist: httpx
Requires-Dist: mcp
